idasen/__init__.py
idasen/cli.py
idasen-0.12.0.dist-info/LICENSE
idasen-0.12.0.dist-info/METADATA
idasen-0.12.0.dist-info/WHEEL
idasen-0.12.0.dist-info/entry_points.txt
idasen-0.12.0.dist-info/RECORD
