Metadata-Version: 2.1
Name: idasen
Version: 0.12.0
Summary: ikea IDÅSEN desk API and CLI.
Home-page: https://github.com/newAM/idasen
License: MIT
Keywords: ikea,idasen,bluetooth,linak,ble
Author: Alex Martens
Author-email: alex@thinglab.org
Requires-Python: >=3.8,<4.0
Classifier: License :: OSI Approved :: MIT License
Classifier: Programming Language :: Python :: 3
Classifier: Programming Language :: Python :: 3.8
Classifier: Programming Language :: Python :: 3.9
Classifier: Programming Language :: Python :: 3.10
Classifier: Programming Language :: Python :: 3.11
Classifier: Programming Language :: Python :: 3.12
Requires-Dist: bleak (>=0.15)
Requires-Dist: pyyaml (>=5.3.1)
Requires-Dist: voluptuous (>=0.12)
Project-URL: Documentation, https://newam.github.io/idasen
Project-URL: Repository, https://github.com/newAM/idasen
